MANIFEST.in
README.rst
TITLE.txt
lh-agpl3-LICENSE.txt
setup.py
./bin/icmEx-clsMethod.py
bisos/__init__.py
bisos.icm.egg-info/PKG-INFO
bisos.icm.egg-info/SOURCES.txt
bisos.icm.egg-info/dependency_links.txt
bisos.icm.egg-info/namespace_packages.txt
bisos.icm.egg-info/not-zip-safe
bisos.icm.egg-info/requires.txt
bisos.icm.egg-info/top_level.txt
bisos/icm/__init__.py
bisos/icm/clsMethod.py
bisos/icm/fp.py
bisos/icm/fpath.py
bisos/icm/shRun.py